Metadata-Version: 2.1
Name: django-cqrs-enkonix
Version: 1.3.2
Summary: Django CQRS data synchronisation
Home-page: https://enkonix.com
Author: Enkonix
License: Apache License, Version 2.0
Keywords: django cqrs sql mixin amqp
Platform: UNKNOWN
Classifier: Development Status :: 5 - Production/Stable
Classifier: Framework :: Django :: 1.11
Classifier: Intended Audience :: Developers
Classifier: License :: OSI Approved :: Apache Software License
Classifier: Operating System :: Unix
Classifier: Programming Language :: Python :: 3.6
Classifier: Programming Language :: Python :: 3.7
Classifier: Programming Language :: Python :: 3.8
Classifier: Topic :: Communications
Classifier: Topic :: Database
Requires-Python: >=3.6
Requires-Dist: Django (>=1.11.20)
Requires-Dist: pika
Requires-Dist: ujson
